llama_index/extractors/entity/__init__.py
llama_index/extractors/entity/base.py
llama_index_extractors_entity-0.4.1.dist-info/METADATA
llama_index_extractors_entity-0.4.1.dist-info/WHEEL
llama_index_extractors_entity-0.4.1.dist-info/licenses/LICENSE
llama_index_extractors_entity-0.4.1.dist-info/RECORD
