Metadata-Version: 2.4
Name: llama-index-extractors-entity
Version: 0.4.1
Summary: llama-index extractors entity integration
Author-email: Your Name <you@example.com>
License-Expression: MIT
License-File: LICENSE
Requires-Python: <4.0,>=3.9
Requires-Dist: huggingface-hub>=0.23.0
Requires-Dist: llama-index-core<0.15,>=0.13.0
Requires-Dist: span-marker>=1.5.0
